bearer/__init__.py
bearer/auth_details.py
bearer/errors.py
tests/__init__.py
tests/test_auth_details.py
tests/test_client.py
bearer-3.1.0.dist-info/LICENSE
bearer-3.1.0.dist-info/METADATA
bearer-3.1.0.dist-info/WHEEL
bearer-3.1.0.dist-info/top_level.txt
bearer-3.1.0.dist-info/RECORD
