Metadata-Version: 2.1
Name: bearer
Version: 3.1.0
Summary: Bearer python helper
Home-page: https://github.com/Bearer/bearer-python
Author: Bearer Team
Author-email: engineering+python@bearer.sh
License: UNKNOWN
Platform: UNKNOWN
Classifier: Programming Language :: Python :: 3
Classifier: License :: OSI Approved :: MIT License
Classifier: Operating System :: OS Independent
Requires-Dist: requests[security] (>=2.9.1)
